chichat/__init__.py
chichat/__main__.py
chichat/app.py
chichat/chatterbox/__init__.py
chichat/chatterbox/mtl_tts.py
chichat/chatterbox/tts.py
chichat/chatterbox/vc.py
chichat/chatterbox/models/utils.py
chichat/chatterbox/models/s3gen/__init__.py
chichat/chatterbox/models/s3gen/const.py
chichat/chatterbox/models/s3gen/decoder.py
chichat/chatterbox/models/s3gen/f0_predictor.py
chichat/chatterbox/models/s3gen/flow.py
chichat/chatterbox/models/s3gen/flow_matching.py
chichat/chatterbox/models/s3gen/hifigan.py
chichat/chatterbox/models/s3gen/s3gen.py
chichat/chatterbox/models/s3gen/xvector.py
chichat/chatterbox/models/s3gen/matcha/decoder.py
chichat/chatterbox/models/s3gen/matcha/flow_matching.py
chichat/chatterbox/models/s3gen/matcha/text_encoder.py
chichat/chatterbox/models/s3gen/matcha/transformer.py
chichat/chatterbox/models/s3gen/transformer/__init__.py
chichat/chatterbox/models/s3gen/transformer/activation.py
chichat/chatterbox/models/s3gen/transformer/attention.py
chichat/chatterbox/models/s3gen/transformer/convolution.py
chichat/chatterbox/models/s3gen/transformer/embedding.py
chichat/chatterbox/models/s3gen/transformer/encoder_layer.py
chichat/chatterbox/models/s3gen/transformer/positionwise_feed_forward.py
chichat/chatterbox/models/s3gen/transformer/subsampling.py
chichat/chatterbox/models/s3gen/transformer/upsample_encoder.py
chichat/chatterbox/models/s3gen/utils/class_utils.py
chichat/chatterbox/models/s3gen/utils/mask.py
chichat/chatterbox/models/s3gen/utils/mel.py
chichat/chatterbox/models/s3gen/utils/mel_old.py
chichat/chatterbox/models/s3tokenizer/__init__.py
chichat/chatterbox/models/s3tokenizer/s3tokenizer.py
chichat/chatterbox/models/t3/__init__.py
chichat/chatterbox/models/t3/llama_configs.py
chichat/chatterbox/models/t3/t3.py
chichat/chatterbox/models/t3/inference/alignment_stream_analyzer.py
chichat/chatterbox/models/t3/inference/alignment_stream_analyzer_new.py
chichat/chatterbox/models/t3/inference/alignment_stream_analyzer_old.py
chichat-0.0.4.dist-info/LICENSE
chichat-0.0.4.dist-info/WHEEL
chichat-0.0.4.dist-info/METADATA
chichat-0.0.4.dist-info/RECORD
