Metadata-Version: 2.1
Name: chichat
Version: 0.0.4
Summary: text-to-speech synthesis lite
Author-email: calcuis <info@calcu.io>
Classifier: License :: OSI Approved :: MIT License
Requires-Dist: librosa
Requires-Dist: s3tokenizer
Requires-Dist: omegaconf
Project-URL: GitHub, https://github.com/calcuis/text-to-speech-synthesis-lite
Project-URL: Issues, https://github.com/calcuis/text-to-speech-synthesis-lite/issues
